occ/ecr_pattern/__init__.py
occ/ecr_pattern/py.typed
occ/ecr_pattern/_jsii/__init__.py
occ/ecr_pattern/_jsii/occ-ecr-pattern@0.0.2.jsii.tgz
occ.ecr_pattern-0.0.2.dist-info/LICENSE
occ.ecr_pattern-0.0.2.dist-info/METADATA
occ.ecr_pattern-0.0.2.dist-info/WHEEL
occ.ecr_pattern-0.0.2.dist-info/top_level.txt
occ.ecr_pattern-0.0.2.dist-info/RECORD
